python_quickbooks3-0.4.1.dist-info/DESCRIPTION.rst
python_quickbooks3-0.4.1.dist-info/METADATA
python_quickbooks3-0.4.1.dist-info/RECORD
python_quickbooks3-0.4.1.dist-info/WHEEL
python_quickbooks3-0.4.1.dist-info/metadata.json
python_quickbooks3-0.4.1.dist-info/pbr.json
python_quickbooks3-0.4.1.dist-info/top_level.txt
quickbooks/__init__.py
quickbooks/batch.py
quickbooks/client.py
quickbooks/exceptions.py
quickbooks/mixins.py
quickbooks/utils.py
quickbooks/objects/__init__.py
quickbooks/objects/account.py
quickbooks/objects/base.py
quickbooks/objects/batchrequest.py
quickbooks/objects/bill.py
quickbooks/objects/billpayment.py
quickbooks/objects/budget.py
quickbooks/objects/creditcardpayment.py
quickbooks/objects/creditmemo.py
quickbooks/objects/customer.py
quickbooks/objects/department.py
quickbooks/objects/deposit.py
quickbooks/objects/detailline.py
quickbooks/objects/employee.py
quickbooks/objects/estimate.py
quickbooks/objects/invoice.py
quickbooks/objects/item.py
quickbooks/objects/journalentry.py
quickbooks/objects/payment.py
quickbooks/objects/paymentmethod.py
quickbooks/objects/purchase.py
quickbooks/objects/purchaseorder.py
quickbooks/objects/refundreceipt.py
quickbooks/objects/salesreceipt.py
quickbooks/objects/tax.py
quickbooks/objects/taxagency.py
quickbooks/objects/taxcode.py
quickbooks/objects/taxrate.py
quickbooks/objects/taxservice.py
quickbooks/objects/term.py
quickbooks/objects/timeactivity.py
quickbooks/objects/transfer.py
quickbooks/objects/vendor.py
quickbooks/objects/vendorcredit.py
quickbooks/tests/__init__.py
quickbooks/tests/unit/__init__.py
quickbooks/tests/unit/test_batch.py
quickbooks/tests/unit/test_client.py
quickbooks/tests/unit/test_exception.py
quickbooks/tests/unit/test_mixins.py
quickbooks/tests/unit/test_utils.py
quickbooks/tests/unit/objects/__init__.py
quickbooks/tests/unit/objects/test_account.py
quickbooks/tests/unit/objects/test_base.py
quickbooks/tests/unit/objects/test_batchrequest.py
quickbooks/tests/unit/objects/test_bill.py
quickbooks/tests/unit/objects/test_billpayment.py
quickbooks/tests/unit/objects/test_budget.py
quickbooks/tests/unit/objects/test_creditcardpayment.py
quickbooks/tests/unit/objects/test_creditmemo.py
quickbooks/tests/unit/objects/test_customer.py
