Metadata-Version: 2.0
Name: python-quickbooks3
Version: 0.4.1
Summary: A Python library for accessing the Quickbooks API. Forked from https://github.com/sidecars/python-quickbooks to improve Python 3 compatibility. Thanks to Edward Emanuel Jr.
Home-page: https://github.com/mattlong/python-quickbooks
Author: Matt Long
Author-email: matt@mattlong.org
License: MIT
Keywords: quickbooks,qbo,accounting
Platform: UNKNOWN
Classifier: Development Status :: 3 - Alpha
Classifier: Intended Audience :: Developers
Classifier: License :: OSI Approved :: MIT License
Classifier: Operating System :: OS Independent
Classifier: Programming Language :: Python
Classifier: Programming Language :: Python :: 2.6
Classifier: Programming Language :: Python :: 2.7
Classifier: Programming Language :: Python :: 3.3
Classifier: Programming Language :: Python :: 3.4
Classifier: Programming Language :: Python :: 3.5
Requires-Dist: python-dateutil
Requires-Dist: rauth (>=0.7.1)
Requires-Dist: requests (>=2.7.0)
Requires-Dist: setuptools
Requires-Dist: simplejson (>=2.2.0)
Requires-Dist: six (>=1.4.0)
